README.md
setup.cfg
setup.py
checkparam/__init__.py
checkparam/checkparam.py
checkparam.egg-info/PKG-INFO
checkparam.egg-info/SOURCES.txt
checkparam.egg-info/dependency_links.txt
checkparam.egg-info/top_level.txt